jh_copy_clipboard.py
jh_gen_prompt.py
jh_prompt_gen-1.0.1.dist-info/licenses/LICENSE
jh_prompt_gen-1.0.1.dist-info/METADATA
jh_prompt_gen-1.0.1.dist-info/WHEEL
jh_prompt_gen-1.0.1.dist-info/entry_points.txt
jh_prompt_gen-1.0.1.dist-info/top_level.txt
jh_prompt_gen-1.0.1.dist-info/RECORD
