Metadata-Version: 2.4
Name: jh-prompt-gen
Version: 1.0.1
Summary: A small toolkit to collect code from local directories and automatically generate ChatGPT prompts.
Author: Dev-CorliJoni
License-Expression: MIT
Project-URL: GitHub, https://github.com/Dev-CorliJoni/jh-prompt-gen
Project-URL: Instagram, https://www.instagram.com/dev.corlijoni/
Keywords: prompt,cli,code,chatgpt,automation
Classifier: Development Status :: 4 - Beta
Classifier: Intended Audience :: Developers
Classifier: Environment :: Console
Classifier: Programming Language :: Python :: 3.7
Classifier: Programming Language :: Python :: 3.8
Classifier: Programming Language :: Python :: 3.9
Classifier: Programming Language :: Python :: 3.10
Classifier: Programming Language :: Python :: 3.11
Classifier: Programming Language :: Python :: 3.12
Classifier: Operating System :: OS Independent
Classifier: Topic :: Software Development :: Code Generators
Requires-Python: >=3.7
License-File: LICENSE
Requires-Dist: pyperclip
Dynamic: license-file
